appkit_mantine/__init__.py
appkit_mantine/action_icon.py
appkit_mantine/autocomplete.py
appkit_mantine/base.py
appkit_mantine/button.py
appkit_mantine/date.py
appkit_mantine/drawer.py
appkit_mantine/inputs.py
appkit_mantine/json_input.py
appkit_mantine/mantine_provider.js
appkit_mantine/markdown_preview.py
appkit_mantine/markdown_preview_wrapper.js
appkit_mantine/markdown_zoom.py
appkit_mantine/masked_input.py
appkit_mantine/mermaid_zoom_loader.js
appkit_mantine/modal.py
appkit_mantine/multi_select.py
appkit_mantine/nav_link.py
appkit_mantine/navigation_progress.js
appkit_mantine/nprogress.py
appkit_mantine/number_formatter.py
appkit_mantine/number_input.py
appkit_mantine/password_input.py
appkit_mantine/react_zoom.py
appkit_mantine/rich_select.jsx
appkit_mantine/rich_select.py
appkit_mantine/scroll_area.py
appkit_mantine/select.py
appkit_mantine/slider.py
appkit_mantine/table.py
appkit_mantine/tags_input.py
appkit_mantine/text_input.py
appkit_mantine/textarea.py
appkit_mantine/tiptap.py
appkit_mantine/tiptap_wrapper.js
appkit_mantine-1.0.1.dist-info/METADATA
appkit_mantine-1.0.1.dist-info/WHEEL
appkit_mantine-1.0.1.dist-info/RECORD
