Metadata-Version: 2.4
Name: appkit-mantine
Version: 1.0.1
Summary: Mantine UI input components for Reflex with type safety and comprehensive examples
Project-URL: Homepage, https://github.com/jenreh/appkit
Project-URL: Documentation, https://github.com/jenreh/appkit/tree/main/docs
Project-URL: Repository, https://github.com/jenreh/appkit
Project-URL: Issues, https://github.com/jenreh/appkit/issues
License: MIT
Keywords: components,forms,input,mantine,react,reflex,ui,web
Classifier: Intended Audience :: Developers
Classifier: License :: OSI Approved :: MIT License
Classifier: Programming Language :: Python :: 3
Classifier: Programming Language :: Python :: 3.13
Classifier: Topic :: Software Development :: Libraries :: Python Modules
Classifier: Topic :: Software Development :: User Interfaces
Requires-Python: >=3.13
Requires-Dist: reflex==0.8.26
